theatron/__init__.py
theatron-0.0.1.dist-info/LICENSE
theatron-0.0.1.dist-info/METADATA
theatron-0.0.1.dist-info/WHEEL
theatron-0.0.1.dist-info/top_level.txt
theatron-0.0.1.dist-info/RECORD
